README.rst
setup.cfg
setup.py
thepay/__init__.py
thepay/config.py
thepay/dataApi.py
thepay/payment.py
thepay/tests.py
thepay/utils.py
thepay.egg-info/PKG-INFO
thepay.egg-info/SOURCES.txt
thepay.egg-info/dependency_links.txt
thepay.egg-info/requires.txt
thepay.egg-info/top_level.txt