Metadata-Version: 1.0
Name: thepay
Version: 0.3
Summary: ThePay API library
Home-page: https://github.com/cuchac/thepay
Author: cuchac
Author-email: cuchac@email.cz
License: LGPL
Platform: UNKNOWN
